kadrovik_g4/__init__.py
kadrovik_g4-1.1.1.dist-info/LICENSE
kadrovik_g4-1.1.1.dist-info/METADATA
kadrovik_g4-1.1.1.dist-info/WHEEL
kadrovik_g4-1.1.1.dist-info/top_level.txt
kadrovik_g4-1.1.1.dist-info/RECORD
